SentenceMatcher.py
SentenceMatcher-0.0.2.dist-info/METADATA
SentenceMatcher-0.0.2.dist-info/WHEEL
SentenceMatcher-0.0.2.dist-info/top_level.txt
SentenceMatcher-0.0.2.dist-info/RECORD
